MDemon/__init__.py
MDemon/analysis/__init__.py
MDemon/analysis/single_atom/__init__.py
MDemon/analysis/single_atom/angular.py
MDemon/analysis/single_atom/base.py
MDemon/analysis/single_atom/coordination.py
MDemon/analysis/single_atom/main.py
MDemon/analysis/single_atom/rdf.py
MDemon/constants/__init__.py
MDemon/constants/chemistry.py
MDemon/constants/conversion.py
MDemon/constants/fundamental.py
MDemon/constants/irradiation.py
MDemon/constants/material.py
MDemon/constants/utils.py
MDemon/core/__init__.py
MDemon/core/database.py
MDemon/core/rw.py
MDemon/core/source.c
MDemon/core/source.cpython-311-darwin.so
MDemon/core/source.pyx
MDemon/core/structure.py
MDemon/core/structureattr.py
MDemon/core/universe.py
MDemon/lib/__init__.py
MDemon/lib/c_distances.c
MDemon/lib/c_distances.cpython-311-darwin.so
MDemon/lib/c_distances.pxd
MDemon/lib/c_distances.pyx
MDemon/lib/distance.py
MDemon/lib/mdamath.py
MDemon/lib/util.py
MDemon/lib/include/calc_distances.h
MDemon/reader/LAMMPS.py
MDemon/reader/REAXFF.py
MDemon/reader/XYZ.py
MDemon/reader/__init__.py
MDemon/reader/base.py
MDemon/selection/__init__.py
MDemon/selection/cylindrical.py
MDemon/utils/__init__.py
MDemon/utils/irradiation.py
MDemon/utils/parallel.py
MDemon/utils/spatial.py
mdemon-0.2.0.dist-info/licenses/LICENSE
mdemon-0.2.0.dist-info/METADATA
mdemon-0.2.0.dist-info/WHEEL
mdemon-0.2.0.dist-info/top_level.txt
mdemon-0.2.0.dist-info/RECORD
