Metadata-Version: 2.4
Name: MDemon
Version: 0.2.0
Summary: Molecular Dynamics Analysis Tool with Cython Extensions
Author-email: Amphilagus <amphilagusjunior@gmail.com>
Maintainer-email: Amphilagus <amphilagusjunior@gmail.com>
License-Expression: GPL-2.0-or-later
Project-URL: Homepage, https://github.com/IMPNanoLabMDTeam/MDemon
Project-URL: Repository, https://github.com/IMPNanoLabMDTeam/MDemon
Project-URL: Issues, https://github.com/IMPNanoLabMDTeam/MDemon/issues
Project-URL: Documentation, https://github.com/IMPNanoLabMDTeam/MDemon/tree/main/docs
Classifier: Development Status :: 4 - Beta
Classifier: Intended Audience :: Science/Research
Classifier: Operating System :: OS Independent
Classifier: Programming Language :: Python :: 3
Classifier: Programming Language :: Python :: 3.9
Classifier: Programming Language :: Python :: 3.10
Classifier: Programming Language :: Python :: 3.11
Classifier: Programming Language :: Python :: 3.12
Classifier: Topic :: Scientific/Engineering :: Chemistry
Classifier: Topic :: Scientific/Engineering :: Physics
Requires-Python: >=3.9
License-File: LICENSE
Requires-Dist: numpy>=1.24.0
Requires-Dist: scipy>=1.10.0
Requires-Dist: pandas>=2.0.0
Requires-Dist: matplotlib>=3.6.0
Requires-Dist: periodictable>=1.5.0
Requires-Dist: seaborn>=0.12.0
Requires-Dist: networkx>=3.2.1
Requires-Dist: jupyter>=1.1.1
Requires-Dist: dask[complete]>=2023.0.0
Requires-Dist: psutil>=5.9.0
Requires-Dist: pre-commit>=4.2.0
Requires-Dist: black>=25.1.0
Requires-Dist: isort>=6.0.1
Provides-Extra: dev
Requires-Dist: black>=24.0.0; extra == "dev"
Requires-Dist: isort>=5.12.0; extra == "dev"
Requires-Dist: ruff>=0.5.0; extra == "dev"
Requires-Dist: pre-commit>=3.0.0; extra == "dev"
Requires-Dist: pytest>=7.0.0; extra == "dev"
Requires-Dist: pytest-cov>=4.0.0; extra == "dev"
Requires-Dist: coverage>=7.0.0; extra == "dev"
Requires-Dist: Cython>=3.0.0; extra == "dev"
Requires-Dist: ipykernel>=6.0.0; extra == "dev"
Requires-Dist: jupyter>=1.0.0; extra == "dev"
Provides-Extra: build
Requires-Dist: Cython>=3.0.0; extra == "build"
Requires-Dist: numpy>=1.24.0; extra == "build"
Dynamic: license-file
